{"BaseModel.45e7b8c8-fab1-45ba-a6ca-4124d8f55262": {"id": "45e7b8c8-fab1-45ba-a6ca-4124d8f55262", "created_at": "2024-01-10T11:54:37.713800", "updated_at": "2024-01-10T11:54:37.713808", "name": "My_First_Model", "my_number": 89, "__class__": "BaseModel"}, "BaseModel.6c3f247b-a18a-4af0-b515-38dfcc7eda58": {"id": "6c3f247b-a18a-4af0-b515-38dfcc7eda58", "created_at": "2024-01-10T12:18:41.022323", "updated_at": "2024-01-10T12:18:41.022328", "name": "My_First_Model", "my_number": 89, "__class__": "BaseModel"}, "BaseModel.92c76588-9ed4-46ff-b066-07e0a6a1c8de": {"id": "92c76588-9ed4-46ff-b066-07e0a6a1c8de", "created_at": "2024-01-10T12:18:55.983249", "updated_at": "2024-01-10T12:18:55.983256", "name": "My_First_Model", "my_number": 89, "__class__": "BaseModel"}, "BaseModel.ec93325e-cebe-4c10-b9c8-a8164e0f6a04": {"id": "ec93325e-cebe-4c10-b9c8-a8164e0f6a04", "created_at": "2024-01-10T12:39:24.962254", "updated_at": "2024-01-10T12:39:24.962260", "name": "My_First_Model", "my_number": 89, "__class__": "BaseModel"}}